cmappertools.cp37-win_amd64.pyd
cmappertools-1.0.26.dist-info/COPYING
cmappertools-1.0.26.dist-info/METADATA
cmappertools-1.0.26.dist-info/WHEEL
cmappertools-1.0.26.dist-info/top_level.txt
cmappertools-1.0.26.dist-info/RECORD
