Metadata-Version: 1.1
Name: cmappertools
Version: 1.0.26
Summary: Optional helper module for the Python Mapper package with fast, parallel C++ algorithms.
Home-page: http://danifold.net
Author: Daniel Müllner
Author-email: daniel@danifold.net
License: GPLv3 <http://www.gnu.org/licenses/gpl.html>
Keywords: Mapper,Topological data analysis,TDA
Platform: UNKNOWN
Classifier: Topic :: Scientific/Engineering :: Information Analysis
Classifier: Topic :: Scientific/Engineering :: Artificial Intelligence
Classifier: Topic :: Scientific/Engineering :: Bio-Informatics
Classifier: Topic :: Scientific/Engineering :: Mathematics
Classifier: Topic :: Scientific/Engineering :: Visualization
Classifier: Programming Language :: Python
Classifier: Programming Language :: Python :: 2
Classifier: Programming Language :: Python :: 3
Classifier: Programming Language :: C++
Classifier: Operating System :: OS Independent
Classifier: License :: OSI Approved :: GNU General Public License v3 (GPLv3)
Classifier: Intended Audience :: Science/Research
Classifier: Development Status :: 5 - Production/Stable
Provides: cmappertools
